mcp_server_ssp/__init__.py
mcp_server_ssp/__main__.py
mcp_server_ssp/http.py
mcp_server_ssp/lesb.py
mcp_server_ssp/server.py
mcp_server_ssp-0.1.1.dist-info/METADATA
mcp_server_ssp-0.1.1.dist-info/WHEEL
mcp_server_ssp-0.1.1.dist-info/entry_points.txt
mcp_server_ssp-0.1.1.dist-info/top_level.txt
mcp_server_ssp-0.1.1.dist-info/RECORD
