Metadata-Version: 2.4
Name: mcp-server-ssp
Version: 0.1.1
Summary: Add your description here
Requires-Python: >=3.12
Requires-Dist: httpx>=0.28.1
Requires-Dist: mcp>=1.23.3
Requires-Dist: pydantic>=2.0.0
